lockstock/__init__.py
lockstock/agent.py
lockstock/exceptions.py
lockstock/types.py
lockstock-0.1.0.dist-info/METADATA
lockstock-0.1.0.dist-info/WHEEL
lockstock-0.1.0.dist-info/top_level.txt
lockstock-0.1.0.dist-info/RECORD
